z3c.authviewlet-2.0-py3.9-nspkg.pth
z3c/authviewlet/README.txt
z3c/authviewlet/__init__.py
z3c/authviewlet/auth.py
z3c/authviewlet/configure.zcml
z3c/authviewlet/ftesting.zcml
z3c/authviewlet/interfaces.py
z3c/authviewlet/login_failed.pt
z3c/authviewlet/login_success.pt
z3c/authviewlet/logout.pt
z3c/authviewlet/logout_head.pt
z3c/authviewlet/redirect.pt
z3c/authviewlet/redirect_head.pt
z3c/authviewlet/session.py
z3c/authviewlet/session_cred_loginform.pt
z3c/authviewlet/tests/__init__.py
z3c/authviewlet/tests/login-logout-template.pt
z3c/authviewlet/tests/test_layer.py
z3c.authviewlet-2.0.dist-info/LICENSE.txt
z3c.authviewlet-2.0.dist-info/METADATA
z3c.authviewlet-2.0.dist-info/WHEEL
z3c.authviewlet-2.0.dist-info/namespace_packages.txt
z3c.authviewlet-2.0.dist-info/top_level.txt
z3c.authviewlet-2.0.dist-info/RECORD
